marker_detection_ai/__init__.py
marker_detection_ai/best_yolov8m.pt
marker_detection_ai/main.py
marker_detection_ai-0.2.0.dist-info/METADATA
marker_detection_ai-0.2.0.dist-info/WHEEL
marker_detection_ai-0.2.0.dist-info/top_level.txt
marker_detection_ai-0.2.0.dist-info/RECORD
