Metadata-Version: 2.1
Name: marker_detection_ai
Version: 0.2.0
Summary: "A marker detection AI"
License: "MIT"
Keywords: ["marker","detection","ai"]
Requires-Dist: numpy
Requires-Dist: opencv-python
Requires-Dist: pillow
Requires-Dist: ultralytics
